{
  "schedules": [
    {
      "id": 1720194564161,
      "name": "Felipe",
      "when": "2024-07-05T17:00:00.000Z"
    },
    {
      "id": 1720194570622,
      "name": "Luís",
      "when": "2024-07-05T19:00:00.000Z"
    },
    {
      "id": 1720194576102,
      "name": "Carol",
      "when": "2024-07-05T20:00:00.000Z"
    },
    {
      "id": 1720194581064,
      "name": "Ângelo",
      "when": "2024-07-05T23:00:00.000Z"
    },
    {
      "id": 1720194586299,
      "name": "Juliano",
      "when": "2024-07-06T01:00:00.000Z"
    },
    {
      "id": 1720194592856,
      "name": "Mari",
      "when": "2024-07-05T16:00:00.000Z"
    }
  ]
}